setup.py
atom/__init__.py
atom/access_pb2.py
atom/access_pb2_grpc.py
atom/dataset_pb2.py
atom/dataset_pb2_grpc.py
atom/device_pb2.py
atom/device_pb2_grpc.py
atom/distributed_pb2.py
atom/distributed_pb2_grpc.py
atom/inference_pb2.py
atom/inference_pb2_grpc.py
atom/job_pb2.py
atom/job_pb2_grpc.py
atom/meta_pb2.py
atom/meta_pb2_grpc.py
atom/ore_pb2.py
atom/ore_pb2_grpc.py
atom/package_pb2.py
atom/package_pb2_grpc.py
atom/profile_pb2.py
atom/profile_pb2_grpc.py
atom/quota_pb2.py
atom/quota_pb2_grpc.py
atom/registry_pb2.py
atom/registry_pb2_grpc.py
atom/secret_pb2.py
atom/secret_pb2_grpc.py
atom/storage_pb2.py
atom/storage_pb2_grpc.py
atom/training_pb2.py
atom/training_pb2_grpc.py
atom/volume_pb2.py
atom/volume_pb2_grpc.py
atom/watch_pb2.py
atom/watch_pb2_grpc.py
atom/github/com/envoyproxy/protoc_gen_validate/validate/__init__.py
atom/github/com/envoyproxy/protoc_gen_validate/validate/validate_pb2.py
atom/interceptors/__init__.py
atom/interceptors/generic_client_interceptor.py
atom/interceptors/header_manipulator_client_interceptor.py
atom_sdk.egg-info/PKG-INFO
atom_sdk.egg-info/SOURCES.txt
atom_sdk.egg-info/dependency_links.txt
atom_sdk.egg-info/requires.txt
atom_sdk.egg-info/top_level.txt