Metadata-Version: 1.2
Name: atom-sdk
Version: 1.1.6
Summary: Atom Python SDK
Home-page: https://pypi.org/project/atom-sdk
Maintainer: Supremind Atom
Maintainer-email: atom@supremind.com
License: UNKNOWN
Platform: UNKNOWN
